hecuba/hfilter.py
hecuba/__init__.py
hecuba/storageobj.py
hecuba/hnumpy.py
hecuba/hdict.py
hecuba/storageiter.py
hecuba/storagestream.py
hecuba/parser.py
hecuba/IStorage.py
hecuba/tools.py
hecuba/qbeast.py
hecuba/hfetch.cpython-310-x86_64-linux-gnu.so
hecuba/lib/libhfetch.so
hecuba/include/ValueClass.h
hecuba/include/MetaManager.h
hecuba/include/KeyClass.h
hecuba/include/FastKVCache.h
hecuba/include/murmur3.hpp
hecuba/include/ArrayDataStore.h
hecuba/include/configmap.h
hecuba/include/AttributeClass.h
hecuba/include/StorageInterface.h
hecuba/include/IStorage.h
hecuba/include/Prefetch.h
hecuba/include/KVCache.h
hecuba/include/TableMetadata.h
hecuba/include/SpaceFillingCurve.h
hecuba/include/TimestampGenerator.h
hecuba/include/HecubaSession.h
hecuba/include/WriterThread.h
hecuba/include/CacheTable.h
hecuba/include/Hecuba_StorageObject.h
hecuba/include/Semaphore.h
hecuba/include/SORecursiveMagic.h
hecuba/include/macros.hpp
hecuba/include/SO_Attribute.h
hecuba/include/dse.h
hecuba/include/ModuleException.h
hecuba/include/StorageObject.h
hecuba/include/UUID.h
hecuba/include/TupleRowFactory.h
hecuba/include/StorageDict.h
hecuba/include/HecubaExtrae.h
hecuba/include/StorageNumpy.h
hecuba/include/debug.h
hecuba/include/TupleRow.h
hecuba/include/ObjSpec.h
hecuba/include/cassandra.h
hecuba/include/StorageStream.h
hecuba/include/SO_ClassName.h
hecuba/include/Writer.h
hecuba/bin/arrow_helper
Hecuba-2.1.2.dist-info/WHEEL
Hecuba-2.1.2.dist-info/top_level.txt
Hecuba-2.1.2.dist-info/RECORD
Hecuba-2.1.2.dist-info/LICENSE.txt
Hecuba-2.1.2.dist-info/METADATA
Hecuba.libs/libtbb-14b91896.so.2
Hecuba.libs/libhfetch-fcdc73e8.so
Hecuba.libs/libuv-4aa576c5.so.1.0.0
Hecuba.libs/librdkafka-cf2ca22b.so.1
Hecuba.libs/libcassandra-56070b1f.so.2.14.1
storage/api.py
storage/__init__.py
storage/ITF/StorageItf-1.0-jar-with-dependencies.jar
